LICENSE
README.md
setup.cfg
setup.py
ReachAnnotation/__init__.py
ReachAnnotation/reachannotation_gui.py
ReachAnnotation/testgui (1).py
ReachAnnotation.egg-info/PKG-INFO
ReachAnnotation.egg-info/SOURCES.txt
ReachAnnotation.egg-info/dependency_links.txt
ReachAnnotation.egg-info/requires.txt
ReachAnnotation.egg-info/top_level.txt