Metadata-Version: 2.1
Name: ReachAnnotation
Version: 0.1.0
Summary: A library intended to generate a GUI to annotate / label video files for the ReachMaster experimental paradigm.Install on python using pip install ReachAnnotate -- Current published version is 0.1.0
Home-page: https://github.com/throneofshadow/ReachAnnotation
Author: Brett Nelson, Nicholas Chin
Author-email: bnelson@lbl.gov
License: BSD-3-Clause-LBNL
Keywords: tkinter,video,player,video player,tkvideoplayer,play video in tkinter,custom annotation
Platform: UNKNOWN
Classifier: Development Status :: 1 - Planning
Classifier: Intended Audience :: Science/Research
Classifier: License :: OSI Approved :: BSD License
Classifier: Operating System :: POSIX :: Linux
Classifier: Programming Language :: Python :: 3
Classifier: Programming Language :: Python :: 3.7
Classifier: Programming Language :: Python :: 3.8
Classifier: Programming Language :: Python :: 3.6
Requires-Python: >=3.6
